pymodelextractor/__init__.py
pymodelextractor/exceptions/__init__.py
pymodelextractor/exceptions/number_of_states_exceeded_exception.py
pymodelextractor/exceptions/query_length_exceeded_exception.py
pymodelextractor/factories/__init__.py
pymodelextractor/factories/lstar_factory.py
pymodelextractor/factories/pdfa_extraction_factory.py
pymodelextractor/learners/__init__.py
pymodelextractor/learners/counterexample_processing/rivest_schapire.py
pymodelextractor/learners/learner.py
pymodelextractor/learners/learning_result.py
pymodelextractor/learners/observation_table_learners/__init__.py
pymodelextractor/learners/observation_table_learners/bounded_lstar_learner.py
pymodelextractor/learners/observation_table_learners/bounded_pdfa_lstar_learner.py
pymodelextractor/learners/observation_table_learners/general_lstar_learner.py
pymodelextractor/learners/observation_table_learners/general_observation_table.py
pymodelextractor/learners/observation_table_learners/lambda_star_learner.py
pymodelextractor/learners/observation_table_learners/lstar_learner.py
pymodelextractor/learners/observation_table_learners/lstarcol_learner.py
pymodelextractor/learners/observation_table_learners/mm_lstar_learner.py
pymodelextractor/learners/observation_table_learners/mm_observation_table.py
pymodelextractor/learners/observation_table_learners/observation_table.py
pymodelextractor/learners/observation_table_learners/pdfa_lstar_learner.py
pymodelextractor/learners/observation_table_learners/pdfa_lstarcol_learner.py
pymodelextractor/learners/observation_table_learners/pdfa_observation_table.py
pymodelextractor/learners/observation_table_learners/translators/__init__.py
pymodelextractor/learners/observation_table_learners/translators/fa_observation_table_translator.py
pymodelextractor/learners/observation_table_learners/translators/mm_observation_table_translator.py
pymodelextractor/learners/observation_table_learners/translators/observation_table_translator.py
pymodelextractor-0.38.2.dist-info/LICENSE
pymodelextractor-0.38.2.dist-info/METADATA
pymodelextractor-0.38.2.dist-info/WHEEL
pymodelextractor-0.38.2.dist-info/RECORD
