Metadata-Version: 2.3
Name: pymodelextractor
Version: 0.38.2
Summary: 
License: Apache 2.0
Author: Federico VIlensky
Author-email: fedevilensky@gmail.com
Requires-Python: >=3.9,<3.11
Classifier: License :: Other/Proprietary License
Classifier: Programming Language :: Python :: 3
Classifier: Programming Language :: Python :: 3.9
Classifier: Programming Language :: Python :: 3.10
Requires-Dist: pythautomata (>=0.41.0,<0.42.0)
Requires-Dist: scikit-learn (>=1.2.1,<2.0.0)
